odoo/addons/account_reconciliation_widget_partial/README.rst
odoo/addons/account_reconciliation_widget_partial/__init__.py
odoo/addons/account_reconciliation_widget_partial/__manifest__.py
odoo/addons/account_reconciliation_widget_partial/i18n/account_reconciliation_widget_partial.pot
odoo/addons/account_reconciliation_widget_partial/i18n/es.po
odoo/addons/account_reconciliation_widget_partial/i18n/it.po
odoo/addons/account_reconciliation_widget_partial/readme/CONTRIBUTORS.rst
odoo/addons/account_reconciliation_widget_partial/readme/DESCRIPTION.rst
odoo/addons/account_reconciliation_widget_partial/readme/USAGE.rst
odoo/addons/account_reconciliation_widget_partial/static/description/icon.png
odoo/addons/account_reconciliation_widget_partial/static/description/index.html
odoo/addons/account_reconciliation_widget_partial/static/description/reconciliation_partial.png
odoo/addons/account_reconciliation_widget_partial/static/src/js/reconciliation_action.js
odoo/addons/account_reconciliation_widget_partial/static/src/js/reconciliation_model.js
odoo/addons/account_reconciliation_widget_partial/static/src/js/reconciliation_renderer.js
odoo/addons/account_reconciliation_widget_partial/static/src/scss/account_reconciliation.scss
odoo/addons/account_reconciliation_widget_partial/static/src/xml/account_reconciliation.xml
odoo/addons/account_reconciliation_widget_partial/views/assets.xml
odoo12_addon_account_reconciliation_widget_partial-12.0.1.0.1.dist-info/METADATA
odoo12_addon_account_reconciliation_widget_partial-12.0.1.0.1.dist-info/WHEEL
odoo12_addon_account_reconciliation_widget_partial-12.0.1.0.1.dist-info/top_level.txt
odoo12_addon_account_reconciliation_widget_partial-12.0.1.0.1.dist-info/RECORD
